SRRec/SRRec.py
SRRec/__init__.py
SRRec/classifier.py
SRRec/config.py
SRRec/coverage.py
SRRec/data_analysis.py
SRRec/data_generation.py
SRRec/data_preprocessing.py
SRRec/encoding.py
SRRec/error_orrection.py
SRRec/isolates_correction.py
SRRec/reads2vectors.py
SRRec/simulation.py
SRRec/umitest.py
SRRec/utils.py
SRRec-0.0.64.dist-info/LICENSE
SRRec-0.0.64.dist-info/METADATA
SRRec-0.0.64.dist-info/WHEEL
SRRec-0.0.64.dist-info/entry_points.txt
SRRec-0.0.64.dist-info/top_level.txt
SRRec-0.0.64.dist-info/RECORD
